django_form_util-0.5.5.dist-info/licenses/LICENSE
form_util/__init__.py
form_util/apps.py
form_util/forms.py
form_util/urls.py
form_util/views.py
form_util/migrations/__init__.py
form_util/models/__init__.py
form_util/static/form_util/style.css
form_util/templates/__init__.py
form_util/templates/form_util/index.html
django_form_util-0.5.5.dist-info/METADATA
django_form_util-0.5.5.dist-info/WHEEL
django_form_util-0.5.5.dist-info/entry_points.txt
django_form_util-0.5.5.dist-info/top_level.txt
django_form_util-0.5.5.dist-info/RECORD
